ikeh-0.1.1.dist-info/licenses/LICENSE
ikehTobrut/__init__.py
ikeh-0.1.1.dist-info/METADATA
ikeh-0.1.1.dist-info/WHEEL
ikeh-0.1.1.dist-info/top_level.txt
ikeh-0.1.1.dist-info/RECORD
