Metadata-Version: 2.4
Name: ikeh
Version: 0.1.1
Summary: Contoh package Python buatan sendiri
Author-email: Ikeh <ikeh@tobrut.com>
License-Expression: MIT
Requires-Python: >=3.7
License-File: LICENSE
Dynamic: license-file
